qregpy/__init__.py
qregpy/qreg.py
qregpy/sampling.py
qregpy-1.1.1.dist-info/LICENSE
qregpy-1.1.1.dist-info/METADATA
qregpy-1.1.1.dist-info/WHEEL
qregpy-1.1.1.dist-info/top_level.txt
qregpy-1.1.1.dist-info/RECORD
