Metadata-Version: 2.1
Name: qregpy
Version: 1.1.1
Summary: Query-centric regression model.
Home-page: https://github.com/qingzma/QReg
Author: Qingzhi Ma
Author-email: Q.Ma.2@warwick.ac.uk
License: Apache License
Requires-Dist: xgboost
Requires-Dist: numpy
Requires-Dist: scikit-learn
